setup.py
distributions/Binomialdistribution.py
distributions/Gaussiandistribution.py
distributions/Generaldistribution.py
distributions/__init__.py
dns_distributions.egg-info/PKG-INFO
dns_distributions.egg-info/SOURCES.txt
dns_distributions.egg-info/dependency_links.txt
dns_distributions.egg-info/not-zip-safe
dns_distributions.egg-info/top_level.txt